{
  "grammar_id": "kg.grammar.ending.discovery_neyo",
  "learner_lang": "zh_tw",
  "title": "-네/네요 (啊/耶 - 感嘆)",
  "explanation_md": "· 用法說明\n直接接在詞幹後。用於表達「原來是這樣啊！」的驚奇感。\n\n· 常見使用場景\n- 親眼看到事實：哇，今天天氣真好耶！\n- 體驗後感悟：這道菜真的很好吃耶。\n- 確認新訊息：原本你是大學生啊。\n\n· 相近文法比較\n- **-군요/구나**: 通用的感嘆，但不一定需要是「剛發現」的事情。\n- **-네요**: 更強調「此刻當下」新發現的事實，口語感非常強。\n\n· 注意\n與第二人稱問句合用時，帶有「原來你...啊？」的確認色彩。",
  "example_sentence_refs": [
    "ex.ko.s.000547",
    "ex.ko.s.000548",
    "ex.ko.s.000549",
    "ex.ko.s.000550",
    "ex.ko.s.000551",
    "ex.ko.s.000552",
    "ex.ko.s.000553",
    "ex.ko.s.000554",
    "ex.ko.s.000555",
    "ex.ko.s.000556"
  ]
}
